hedy/Dockerfile.debian
hedy/Dockerfile.stage
hedy/__init__.py
hedy/_version.py
hedy/cli.py
hedy/tasks.py
hedy-0.0.2.dist-info/METADATA
hedy-0.0.2.dist-info/WHEEL
hedy-0.0.2.dist-info/entry_points.txt
hedy-0.0.2.dist-info/top_level.txt
hedy-0.0.2.dist-info/RECORD
