Metadata-Version: 2.1
Name: hedy
Version: 0.0.2
Summary: UNKNOWN
Home-page: https://github.com/avengerpenguin/hedy
Author: Ross Fenning
Author-email: github@rossfenning.co.uk
License: UNKNOWN
Project-URL: Issue Tracker, https://github.com/avengerpenguin/hedy/issues
Keywords: pelican,invoke
Platform: UNKNOWN
Classifier: License :: OSI Approved :: GNU General Public License v3 (GPLv3)
Classifier: Development Status :: 5 - Production/Stable
Classifier: Intended Audience :: Developers
Classifier: Operating System :: Unix
Classifier: Operating System :: POSIX
Classifier: Programming Language :: Python
Classifier: Programming Language :: Python :: 3
Classifier: Programming Language :: Python :: 3.5
Classifier: Programming Language :: Python :: 3.6
Classifier: Programming Language :: Python :: 3.7
Classifier: Programming Language :: Python :: 3.8
Classifier: Programming Language :: Python :: Implementation :: CPython
Classifier: Topic :: Internet :: WWW/HTTP
Requires-Dist: invoke
Requires-Dist: livereload
Provides-Extra: test
Requires-Dist: pytest ; extra == 'test'
Requires-Dist: pytest-pikachu ; extra == 'test'
Requires-Dist: pytest-mypy ; extra == 'test'
